watlow/__init__.py
watlow/driver.py
watlow/mock.py
watlow/util.py
watlow-0.8.1.dist-info/LICENSE
watlow-0.8.1.dist-info/METADATA
watlow-0.8.1.dist-info/WHEEL
watlow-0.8.1.dist-info/entry_points.txt
watlow-0.8.1.dist-info/top_level.txt
watlow-0.8.1.dist-info/RECORD
