Metadata-Version: 2.2
Name: watlow
Version: 0.8.1
Summary: Python driver for Watlow EZ-Zone temperature controllers.
Author-email: Pat Fuller <patrickfuller@gmail.com>
Maintainer-email: Alex Ruddick <alex@ruddick.tech>
Project-URL: Homepage, https://github.com/alexrudd2/watlow/
Project-URL: Issues, https://github.com/alexrudd2/watlow/issues
Classifier: License :: OSI Approved :: GNU General Public License v2 (GPLv2)
Classifier: Development Status :: 4 - Beta
Classifier: Natural Language :: English
Classifier: Programming Language :: Python
Classifier: Programming Language :: Python :: 3
Classifier: Programming Language :: Python :: 3.9
Classifier: Programming Language :: Python :: 3.10
Classifier: Programming Language :: Python :: 3.11
Classifier: Programming Language :: Python :: 3.12
Classifier: Programming Language :: Python :: 3.13
Classifier: Topic :: Scientific/Engineering :: Human Machine Interfaces
Classifier: Topic :: Scientific/Engineering :: Electronic Design Automation (EDA)
License-File: LICENSE
Requires-Dist: pymodbus>=2.4.0; python_version == "3.9"
Requires-Dist: pymodbus<3.9.0,>=3.0.2; python_version >= "3.10"
Requires-Dist: pyserial
Requires-Dist: crcmod
Provides-Extra: test
Requires-Dist: mypy==1.14.1; extra == "test"
Requires-Dist: pytest; extra == "test"
Requires-Dist: pytest-cov; extra == "test"
Requires-Dist: pytest-asyncio; extra == "test"
Requires-Dist: ruff==0.8.4; extra == "test"
Requires-Dist: types-pyserial; extra == "test"
